[
	{
		"id": "1",
		"title": "Front-end",
		"content": [
			{
				"id": "1",
				"name": "HTML",
				"image": "/src/assets/HTML.png"
			},
			{
				"id": "2",
				"name": "CSS",
				"image": "/src/assets/CSS.png"
			},
			{
				"id": "3",
				"name": "Sass",
				"image": "/src/assets/Sass.png"
			},
			{
				"id": "4",
				"name": "JavaScript",
				"image": "/src/assets/JavaScript.png"
			},
			{
				"id": "5",
				"name": "React",
				"image": "/src/assets/React.png"
			}
		]
	},
	{
		"id": "2",
		"title": "Back-end",
		"content": [
			{
				"id": "1",
				"name": "NodeJS",
				"image": "/src/assets/NodeJS.png"
			},
			{
				"id": "2",
				"name": "ExpressJS",
				"image": "/src/assets/ExpressJS.png"
			},
			{
				"id": "3",
				"name": "MongoDB",
				"image": "/src/assets/MongoDB.png"
			}
		]
	},
	{
		"id": "3",
		"title": "Autres",
		"content": [
			{
				"id": "1",
				"name": "Git (et GitHub)",
				"image": "/src/assets/Git.png"
			},
			{
				"id": "2",
				"name": "Postman",
				"image": "/src/assets/Postman.png"
			}
		]
	}
]